panzoom/__init__.py
panzoom/cli.py
panzoom-0.1.2.dist-info/METADATA
panzoom-0.1.2.dist-info/WHEEL
panzoom-0.1.2.dist-info/entry_points.txt
panzoom-0.1.2.dist-info/top_level.txt
panzoom-0.1.2.dist-info/RECORD
