Metadata-Version: 2.1
Name: panzoom
Version: 0.1.2
Summary: A CLI tool for creating pan and zoom videos from images.
Home-page: https://github.com/nzee/panzoom
Author: Nazim Zeeshan
Author-email: nazim.zeeshan@gmail.com
License: MIT
Platform: UNKNOWN
Classifier: Programming Language :: Python :: 3
Classifier: License :: OSI Approved :: MIT License
Requires-Dist: numpy
Requires-Dist: opencv-python
Requires-Dist: Pillow
Requires-Dist: requests
